bmrb_sans-1.0.0.dist-info/licenses/LICENSE
sans/CifParser.py
sans/DicParser.py
sans/SansParser.py
sans/__init__.py
sans/handlers.py
sans/lexer.py
bmrb_sans-1.0.0.dist-info/METADATA
bmrb_sans-1.0.0.dist-info/WHEEL
bmrb_sans-1.0.0.dist-info/top_level.txt
bmrb_sans-1.0.0.dist-info/RECORD
